setup.py
oxente/__init__.py
oxente/__main__.py
oxente.egg-info/PKG-INFO
oxente.egg-info/SOURCES.txt
oxente.egg-info/dependency_links.txt
oxente.egg-info/requires.txt
oxente.egg-info/top_level.txt