Metadata-Version: 1.1
Name: oxente
Version: 1.0
Summary: Tradução do módulo "this" do python para PT-BR-NE (Português brasileiro nordestino)
Home-page: https://github.com/luanfonceca/oxente
Author: Luan Fonseca
Author-email: luanfonceca@gmail.com
License: MIT
Platform: UNKNOWN
Classifier: Development Status :: 3 - Alpha
Classifier: Environment :: Web Environment
Classifier: Intended Audience :: Developers
Classifier: License :: OSI Approved :: MIT License
Classifier: Natural Language :: English
Classifier: Operating System :: OS Independent
Classifier: Programming Language :: Python
